napari_grid_cropping/__init__.py
napari_grid_cropping/_annotating.py
napari_grid_cropping/_cropping.py
napari_grid_cropping/_version.py
napari_grid_cropping/napari.yaml
napari_grid_cropping/_tests/__init__.py
napari_grid_cropping/_tests/test_widget.py
napari_grid_cropping-0.0.1.dist-info/LICENSE
napari_grid_cropping-0.0.1.dist-info/METADATA
napari_grid_cropping-0.0.1.dist-info/WHEEL
napari_grid_cropping-0.0.1.dist-info/entry_points.txt
napari_grid_cropping-0.0.1.dist-info/top_level.txt
napari_grid_cropping-0.0.1.dist-info/RECORD
