Metadata-Version: 2.1
Name: napari-grid-cropping
Version: 0.0.1
Summary: Create multiple crops of an image in a grid like fashion.
Author: Niklas Breitenbach-Netter
Author-email: niknett@gmail.com
License: 
Project-URL: Bug Tracker, https://github.com/gatoniel/napari-grid-cropping/issues
Project-URL: Documentation, https://github.com/gatoniel/napari-grid-cropping#README.md
Project-URL: Source Code, https://github.com/gatoniel/napari-grid-cropping
Project-URL: User Support, https://github.com/gatoniel/napari-grid-cropping/issues
Classifier: Development Status :: 2 - Pre-Alpha
Classifier: Framework :: napari
Classifier: Intended Audience :: Developers
Classifier: License :: OSI Approved :: BSD License
Classifier: Operating System :: OS Independent
Classifier: Programming Language :: Python
Classifier: Programming Language :: Python :: 3
Classifier: Programming Language :: Python :: 3 :: Only
Classifier: Programming Language :: Python :: 3.9
Classifier: Programming Language :: Python :: 3.10
Classifier: Programming Language :: Python :: 3.11
Classifier: Programming Language :: Python :: 3.12
Classifier: Topic :: Scientific/Engineering :: Image Processing
Requires-Python: >=3.9
License-File: LICENSE
Requires-Dist: numpy
Requires-Dist: qtpy
Requires-Dist: tifffile
Provides-Extra: testing
Requires-Dist: tox; extra == "testing"
Requires-Dist: pytest; extra == "testing"
Requires-Dist: pytest-cov; extra == "testing"
Requires-Dist: pytest-qt; extra == "testing"
Requires-Dist: napari; extra == "testing"
Requires-Dist: pyqt5; extra == "testing"
Requires-Dist: magicgui; extra == "testing"
